orange3_scoring-0.0.1-py3.7-nspkg.pth
orangecontrib/scoring/__init__.py
orangecontrib/scoring/lib/__init__.py
orangecontrib/scoring/lib/model.py
orangecontrib/scoring/lib/readers.py
orangecontrib/scoring/lib/utils.py
orangecontrib/scoring/tests/__init__.py
orangecontrib/scoring/tests/sample_iris.json
orangecontrib/scoring/tests/sample_pfa.json
orangecontrib/scoring/tests/sample_pmml.xml
orangecontrib/scoring/tests/test_owloadmodel.py
orangecontrib/scoring/tutorials/__init__.py
orangecontrib/scoring/widgets/__init__.py
orangecontrib/scoring/widgets/owevaluate.py
orangecontrib/scoring/widgets/owloadmodel.py
orangecontrib/scoring/widgets/icons/category.svg
orangecontrib/scoring/widgets/icons/evaluate.svg
orangecontrib/scoring/widgets/icons/model.svg
orangecontrib/scoring/widgets/icons/pfa.svg
orangecontrib/scoring/widgets/icons/pmml.svg
orange3_scoring-0.0.1.dist-info/LICENSE
orange3_scoring-0.0.1.dist-info/METADATA
orange3_scoring-0.0.1.dist-info/WHEEL
orange3_scoring-0.0.1.dist-info/entry_points.txt
orange3_scoring-0.0.1.dist-info/namespace_packages.txt
orange3_scoring-0.0.1.dist-info/top_level.txt
orange3_scoring-0.0.1.dist-info/RECORD
