Metadata-Version: 2.1
Name: orange3-scoring
Version: 0.0.1
Summary: Add-on containing scoring engine widgets for PFA, PMML and ONNX (coming soon) models
Home-page: https://github.com/animator/orange3-scoring
Author: Ankit Mahato
Author-email: ankmahato@gmail.com
License: MIT
Keywords: orange3 add-on,scoring,inference,pfa,pmml,onnx
Platform: UNKNOWN
Classifier: Development Status :: 3 - Alpha
Classifier: Intended Audience :: Developers
Classifier: Intended Audience :: Education
Classifier: Intended Audience :: Information Technology
Classifier: Intended Audience :: Science/Research
Classifier: Topic :: Scientific/Engineering
Classifier: Topic :: Scientific/Engineering :: Artificial Intelligence
Classifier: Topic :: Software Development
Classifier: Topic :: Software Development :: Libraries
Classifier: Topic :: Software Development :: Libraries :: Python Modules
Classifier: License :: OSI Approved :: MIT License
Classifier: Programming Language :: Python :: 3 :: Only
Classifier: Programming Language :: Python :: 3
Classifier: Programming Language :: Python :: 3.5
Classifier: Programming Language :: Python :: 3.6
Classifier: Programming Language :: Python :: 3.7
Classifier: Programming Language :: Python :: 3.8
Classifier: Natural Language :: English
Requires-Python: >=3.5
Requires-Dist: Orange3
Requires-Dist: titus2
Requires-Dist: pypmml
